retina/__init__.py
retina/__version__.py
retina/core.py
retina/adapters/__init__.py
retina/adapters/filer.py
retina-0.0.2.dist-info/LICENSE
retina-0.0.2.dist-info/METADATA
retina-0.0.2.dist-info/WHEEL
retina-0.0.2.dist-info/top_level.txt
retina-0.0.2.dist-info/RECORD
