Metadata-Version: 2.1
Name: retina
Version: 0.0.2
Summary: Painless retina image handling
Home-page: https://github.com/dreipol/retina
Author: dreipol
Author-email: dev@dreipol.ch
License: MIT
Platform: UNKNOWN
Classifier: License :: OSI Approved :: MIT License
Classifier: Programming Language :: Python
Classifier: Programming Language :: Python :: 3
Classifier: Programming Language :: Python :: 3.6
Classifier: Programming Language :: Python :: Implementation :: CPython
Classifier: Programming Language :: Python :: Implementation :: PyPy
Requires-Python: >=3.6.0
